acropolis/__init__.py
acropolis/cache.py
acropolis/cascade.py
acropolis/db.py
acropolis/flags.py
acropolis/info.py
acropolis/input.py
acropolis/jit.py
acropolis/models.py
acropolis/nucl.py
acropolis/obs.py
acropolis/params.py
acropolis/plots.py
acropolis/pprint.py
acropolis/scans.py
acropolis/utils.py
acropolis/data/alterbbn_v2_2_failsafe_12.tar.gz
acropolis/data/rates.db.gz
acropolis/data/sm.tar.gz
acropolis/ext/__init__.py
acropolis/ext/benchmarks.py
acropolis/ext/models.py
acropolis-1.3.1.data/scripts/annihilation
acropolis-1.3.1.data/scripts/decay
acropolis-1.3.1.dist-info/LICENSE
acropolis-1.3.1.dist-info/METADATA
acropolis-1.3.1.dist-info/WHEEL
acropolis-1.3.1.dist-info/top_level.txt
acropolis-1.3.1.dist-info/RECORD
