Metadata-Version: 2.2
Name: ACROPOLIS
Version: 1.3.1
Summary: A generiC fRamework fOr Photodisintegration Of LIght elementS
Home-page: https://acropolis.hepforge.org
Author: Paul Frederik Depta, Marco Hufnagel, Kai Schmidt-Hoberg
License: GPL3
Requires-Python: >=3.6
License-File: LICENSE
Requires-Dist: numpy>=1.19.1
Requires-Dist: scipy>=1.5.2
Requires-Dist: numba>=0.51.2
Dynamic: author
Dynamic: description
Dynamic: description-content-type
Dynamic: home-page
Dynamic: license
Dynamic: requires-dist
Dynamic: requires-python
Dynamic: summary
